beprint/__init__.py
beprint/ansi.py
beprint/beprint.py
beprint/highlight_code.py
beprint/markdown.py
beprint/layout/__init__.py
beprint/layout/align.py
beprint/layout/base.py
beprint/layout/border.py
beprint/layout/chars.py
beprint/layout/columns.py
beprint/layout/panel.py
beprint/layout/table.py
beprint-0.1.3.dist-info/LICENSE.txt
beprint-0.1.3.dist-info/METADATA
beprint-0.1.3.dist-info/WHEEL
beprint-0.1.3.dist-info/top_level.txt
beprint-0.1.3.dist-info/RECORD
