Metadata-Version: 2.1
Name: beprint
Version: 0.1.3
Summary: BePrint -- Make Your Python Print Statements Beautiful
Home-page: https://github.com/IsBenben/beprint
Author: IsBenben
License: Apache License
Classifier: Programming Language :: Python :: 3
Classifier: Operating System :: OS Independent
Classifier: Natural Language :: Chinese (Simplified)
Requires-Python: >=3.11
License-File: LICENSE.txt
Requires-Dist: Pygments
Requires-Dist: mistune
